Anifetch/Anifetch.py
Anifetch/__init__.py
Anifetch/ascii_arts.py
anifetch-0.1.0.dist-info/METADATA
anifetch-0.1.0.dist-info/WHEEL
anifetch-0.1.0.dist-info/entry_points.txt
anifetch-0.1.0.dist-info/top_level.txt
anifetch-0.1.0.dist-info/RECORD
